{
  "vBRIEFInfo": {
    "version": "0.5",
    "author": "agent:warp-oz",
    "description": "Fix support ticket dark mode card readability",
    "created": "2026-03-21T22:04:43Z"
  },
  "plan": {
    "id": "fix-support-ticket-dark-mode-cards",
    "title": "Fix support ticket card text unreadable in dark/night mode",
    "status": "completed",
    "tags": ["frontend", "dark-mode", "support"],
    "items": [
      {
        "id": "entry-type-config",
        "title": "Add dark: variants to ENTRY_TYPE_CONFIG in ticket-timeline.tsx",
        "status": "completed"
      },
      {
        "id": "status-badges",
        "title": "Add dark: variants to STATUS_STYLES and STATUS_BADGE maps",
        "status": "completed"
      },
      {
        "id": "stats-strip",
        "title": "Add dark: variants to stats strip in support-management-view.tsx",
        "status": "completed"
      },
      {
        "id": "misc-elements",
        "title": "Add dark: variants to org badge, error banners, DEFT Only badge",
        "status": "completed"
      },
      {
        "id": "verify-tests",
        "title": "Run task test to verify no regressions",
        "status": "completed"
      }
    ]
  }
}
